risesdk/__init__.py
risesdk/api/__init__.py
risesdk/api/accounts.py
risesdk/api/base.py
risesdk/api/blocks.py
risesdk/api/client.py
risesdk/api/delegates.py
risesdk/api/transactions.py
risesdk/protocol/__init__.py
risesdk/protocol/primitives.py
risesdk/protocol/transactions.py
risesdk-0.10.0.dist-info/METADATA
risesdk-0.10.0.dist-info/WHEEL
risesdk-0.10.0.dist-info/top_level.txt
risesdk-0.10.0.dist-info/RECORD
