Metadata-Version: 2.1
Name: risesdk
Version: 0.10.0
Summary: APIs for interacting with the RISE blockchain
Home-page: https://rise.vision/
Author: Mart Roosmaa
Author-email: mart@rise.vision
License: MIT
Keywords: rise sdk risesdk crypto currency cryptocurrency risevision altcoin
Platform: UNKNOWN
Classifier: Development Status :: 3 - Alpha
Classifier: Intended Audience :: Developers
Classifier: Topic :: Software Development
Classifier: License :: OSI Approved :: MIT License
Classifier: Programming Language :: Python :: 3
Classifier: Programming Language :: Python :: 3.6
Classifier: Programming Language :: Python :: 3.7
Requires-Dist: requests
Requires-Dist: ed25519
